LICENSE
MANIFEST.in
README.md
pyproject.toml
setup.py
cometa.egg-info/PKG-INFO
cometa.egg-info/SOURCES.txt
cometa.egg-info/dependency_links.txt
cometa.egg-info/requires.txt
cometa.egg-info/top_level.txt
simba/__init__.py
simba/constants.py
simba/db.py
simba/exceptions.py
simba/bayesian/isoclustcython.c
simba/annotation/__init__.py
simba/annotation/annotator.py
simba/annotation/candidates.py
simba/annotation/features.py
simba/annotation/helper_links.py
simba/annotation/helper_priors.py
simba/annotation/isomers_cluster.py
simba/annotation/postprocessing.py
simba/annotation/scoring.py
simba/annotation/generic/__init__.py
simba/annotation/generic/abstract_link.py
simba/annotation/generic/candidate_link.py
simba/annotation/generic/prior_match.py
simba/annotation/links/__init__.py
simba/annotation/links/adducts.py
simba/annotation/links/chemsim.py
simba/annotation/links/gem.py
simba/annotation/links/homologous.py
simba/annotation/links/homologous_functions.py
simba/annotation/links/ipa_form_diff.py
simba/annotation/links/msms_network.py
simba/annotation/prior/__init__.py
simba/annotation/prior/ms2.py
simba/annotation/prior/structural_property.py
simba/bayesian/__init__.py
simba/bayesian/estimate_betamix.py
simba/bayesian/isoclustcython.c
simba/bayesian/mass_prior.py
simba/bayesian/mixture_similarity.py
simba/data/__init__.py
simba/data/chebi.csv
simba/entities/__init__.py
simba/entities/adduct.py
simba/entities/entity.py
simba/entities/molecule.py
simba/entities/representation.py
simba/entities/feature/__init__.py
simba/entities/feature/feature_matrix.py
simba/io/__init__.py
simba/io/exporter.py
simba/io/fullstorer.py
simba/io/gem.py
simba/io/input_utils.py
simba/io/samples_parser.py
simba/io/storage.py
simba/similarities/__init__.py
simba/similarities/abstract_similarity.py
simba/similarities/molecular_similarity.py
simba/tests/__init__.py
simba/tests/test_dataset.py
simba/tests/test_entities.py
simba/utils/__init__.py
simba/utils/arguments_checking.py
simba/utils/build_fingerprints.py
simba/utils/chunks.py
simba/utils/distributions.py
simba/utils/lsh.py
simba/utils/matching.py
simba/utils/parallel_extension.py
