Metadata-Version: 2.1
Name: cometa
Version: 0.1.69
Summary: Metabolomics data annotation
Home-page: https://github.com/adelabriere/SimBa
Author: Alexis Delabriere, Zamboni Lab, ETH Zurich
Author-email: delabriere@imsb.biol.ethz.ch
License: MIT
Platform: UNKNOWN
Classifier: Programming Language :: Python :: 3
Classifier: License :: OSI Approved :: MIT License
Classifier: Operating System :: OS Independent
Requires-Python: >=3.6
License-File: LICENSE
